pythtb/__init__.py
pythtb/hoptable.py
pythtb/lattice.py
pythtb/mesh.py
pythtb/tbmodel.py
pythtb/utils.py
pythtb/w90.py
pythtb/wannier.py
pythtb/wfarray.py
pythtb/io/__init__.py
pythtb/io/qe.py
pythtb/io/w90.py
pythtb/models/__init__.py
pythtb/models/checkerboard.py
pythtb/models/fu_kane_mele.py
pythtb/models/graphene.py
pythtb/models/haldane.py
pythtb/models/kane_mele.py
pythtb/models/ssh.py
pythtb/visualization/__init__.py
pythtb/visualization/lattice.py
pythtb/visualization/tbmodel.py
pythtb/visualization/utils.py
pythtb/visualization/wannier.py
pythtb-2.0.1.dist-info/licenses/LICENSE
pythtb-2.0.1.dist-info/METADATA
pythtb-2.0.1.dist-info/WHEEL
pythtb-2.0.1.dist-info/top_level.txt
pythtb-2.0.1.dist-info/RECORD
