Metadata-Version: 2.4
Name: pythtb
Version: 2.0.1
Summary: Python library for constructing and analyzing tight-binding models.
Author-email: Trey Cole <trey@treycole.me>, Sinisa Coh <sinisacoh@gmail.com>, David Vanderbilt <dhv@physics.rutgers.edu>
Maintainer-email: Trey Cole <trey@treycole.me>, David Vanderbilt <dhv@physics.rutgers.edu>
License-Expression: GPL-3.0-or-later
Project-URL: homepage, https://www.physics.rutgers.edu/pythtb/
Project-URL: documentation, https://pythtb.readthedocs.io/en/latest/
Project-URL: source, https://github.com/pythtb/pythtb
Project-URL: issues, https://github.com/pythtb/pythtb/issues
Project-URL: changelog, https://github.com/pythtb/pythtb/blob/main/CHANGELOG.md
Keywords: physics,tight binding,solid state physics,condensed matter physics,materials science
Classifier: Programming Language :: Python :: 3 :: Only
Classifier: Programming Language :: Python :: 3.12
Classifier: Programming Language :: Python :: 3.13
Classifier: Operating System :: OS Independent
Classifier: Intended Audience :: Science/Research
Classifier: Topic :: Scientific/Engineering :: Physics
Requires-Python: >=3.12
License-File: LICENSE
Requires-Dist: numpy>=2.0
Requires-Dist: matplotlib>=3.9
Provides-Extra: docs
Requires-Dist: sphinx; extra == "docs"
Requires-Dist: pydata-sphinx-theme; extra == "docs"
Requires-Dist: sphinx-copybutton; extra == "docs"
Requires-Dist: myst-nb; extra == "docs"
Requires-Dist: sphinxcontrib-programoutput; extra == "docs"
Requires-Dist: nbconvert; extra == "docs"
Requires-Dist: sphinx-design; extra == "docs"
Requires-Dist: sphinx-gallery; extra == "docs"
Requires-Dist: numpydoc; extra == "docs"
Requires-Dist: sphinx-togglebutton; extra == "docs"
Requires-Dist: sphinx-notfound-page; extra == "docs"
Provides-Extra: tests
Requires-Dist: pytest; extra == "tests"
Provides-Extra: dev
Requires-Dist: pytest; extra == "dev"
Requires-Dist: black; extra == "dev"
Requires-Dist: pre-commit; extra == "dev"
Requires-Dist: ruff; extra == "dev"
Requires-Dist: nbstripout; extra == "dev"
Provides-Extra: plotting
Requires-Dist: plotly; extra == "plotting"
Provides-Extra: speedup
Requires-Dist: tensorflow; extra == "speedup"
Provides-Extra: notebooks
Requires-Dist: jupyter; extra == "notebooks"
Requires-Dist: jupyterlab; extra == "notebooks"
Requires-Dist: notebook>=7.0; extra == "notebooks"
Requires-Dist: ipykernel; extra == "notebooks"
Requires-Dist: ipython>=8.17; extra == "notebooks"
Dynamic: license-file
